jupyterlite_remote_server/__init__.py
jupyterlite_remote_server/_version.py
jupyterlite_remote_server-0.2.0.data/data/share/jupyter/labextensions/jupyterlite-remote-server/package.json
jupyterlite_remote_server-0.2.0.data/data/share/jupyter/labextensions/jupyterlite-remote-server/static/134.c6c38b8897474f7942a4.js
jupyterlite_remote_server-0.2.0.data/data/share/jupyter/labextensions/jupyterlite-remote-server/static/728.d01810ffa6cc546d9e97.js
jupyterlite_remote_server-0.2.0.data/data/share/jupyter/labextensions/jupyterlite-remote-server/static/remoteEntry.36b538df0d32a182ac16.js
jupyterlite_remote_server-0.2.0.data/data/share/jupyter/labextensions/jupyterlite-remote-server/static/style.js
jupyterlite_remote_server-0.2.0.data/data/share/jupyter/labextensions/jupyterlite-remote-server/static/third-party-licenses.json
jupyterlite_remote_server-0.2.0.data/data/share/jupyter/labextensions/jupyterlite-remote-server/install.json
jupyterlite_remote_server-0.2.0.dist-info/METADATA
jupyterlite_remote_server-0.2.0.dist-info/WHEEL
jupyterlite_remote_server-0.2.0.dist-info/licenses/LICENSE
jupyterlite_remote_server-0.2.0.dist-info/RECORD
