Metadata-Version: 2.4
Name: jupyterlite_remote_server
Version: 0.2.0
Summary: JupyterLite extension to connect to a remote Jupyter server
Project-URL: Homepage, https://github.com/jtpio/jupyterlite-remote-server
Project-URL: Bug Tracker, https://github.com/jtpio/jupyterlite-remote-server/issues
Project-URL: Repository, https://github.com/jtpio/jupyterlite-remote-server.git
Author: Jeremy Tuloup
License: BSD 3-Clause License
License-File: LICENSE
Keywords: jupyter,jupyterlab,jupyterlab-extension,jupyterlite,jupyterlite-extension
Classifier: Framework :: Jupyter
Classifier: Framework :: Jupyter :: JupyterLab
Classifier: Framework :: Jupyter :: JupyterLab :: 4
Classifier: Framework :: Jupyter :: JupyterLab :: Extensions
Classifier: Framework :: Jupyter :: JupyterLab :: Extensions :: Prebuilt
Classifier: License :: OSI Approved :: BSD License
Classifier: Programming Language :: Python
Classifier: Programming Language :: Python :: 3
Classifier: Programming Language :: Python :: 3.10
Classifier: Programming Language :: Python :: 3.11
Classifier: Programming Language :: Python :: 3.12
Classifier: Programming Language :: Python :: 3.13
Classifier: Programming Language :: Python :: 3.14
Requires-Python: >=3.10
